topsim/__init__.py
topsim/best.py
topsim/grammap.py
topsim/localtyping.py
topsim/setsimilarity.py
topsim-0.2.0.dist-info/METADATA
topsim-0.2.0.dist-info/WHEEL
topsim-0.2.0.dist-info/entry_points.txt
topsim-0.2.0.dist-info/licenses/LICENSE
topsim-0.2.0.dist-info/RECORD
