Metadata-Version: 2.4
Name: TopSim
Version: 0.2.0
Summary: Search the most similar strings against the query in Python 3.
Project-URL: Repository, https://github.com/chuanconggao/TopSim
Author-email: Chuancong Gao <chuanconggao@users.noreply.github.com>
License-Expression: MIT
License-File: LICENSE
Keywords: similarity-search,string-search
Classifier: Operating System :: OS Independent
Classifier: Programming Language :: Python
Classifier: Programming Language :: Python :: 3
Requires-Python: >=3.12
Requires-Dist: docopt-ng>=0.9.0
Requires-Dist: extratools-core>=0.1.0
